livef1/__init__.py
livef1/api.py
livef1/adapters/__init__.py
livef1/adapters/functions.py
livef1/adapters/livetimingf1_adapter.py
livef1/adapters/other.py
livef1/adapters/realtime_client.py
livef1/adapters/signalr_aio/__init__.py
livef1/adapters/signalr_aio/_connection.py
livef1/adapters/signalr_aio/events/__init__.py
livef1/adapters/signalr_aio/events/_events.py
livef1/adapters/signalr_aio/hubs/__init__.py
livef1/adapters/signalr_aio/hubs/_hub.py
livef1/adapters/signalr_aio/transports/__init__.py
livef1/adapters/signalr_aio/transports/_exceptions.py
livef1/adapters/signalr_aio/transports/_parameters.py
livef1/adapters/signalr_aio/transports/_queue_events.py
livef1/adapters/signalr_aio/transports/_transport.py
livef1/data_processing/__init__.py
livef1/data_processing/data_models.py
livef1/data_processing/etl.py
livef1/data_processing/lakes.py
livef1/data_processing/parse_functions.py
livef1/data_processing/silver_functions.py
livef1/models/__init__.py
livef1/models/circuit.py
livef1/models/driver.py
livef1/models/meeting.py
livef1/models/season.py
livef1/models/session.py
livef1/utils/__init__.py
livef1/utils/constants.py
livef1/utils/exceptions.py
livef1/utils/helper.py
livef1/utils/logger.py
livef1-1.0.972.dist-info/licenses/LICENSE
livef1-1.0.972.dist-info/METADATA
livef1-1.0.972.dist-info/WHEEL
livef1-1.0.972.dist-info/top_level.txt
livef1-1.0.972.dist-info/RECORD
