Metadata-Version: 2.4
Name: livef1
Version: 1.0.972
Summary: A Python toolkit for seamless access to live and historical Formula 1 data.
Home-page: https://github.com/GoktugOcal/LiveF1
Author: Göktuğ Öcal
License: MIT
Project-URL: Bug Tracker, https://github.com/GoktugOcal/LiveF1/issues
Project-URL: Documentation, https://github.com/GoktugOcal/LiveF1#readme
Project-URL: Source Code, https://github.com/GoktugOcal/LiveF1
Classifier: Programming Language :: Python :: 3
Classifier: License :: OSI Approved :: MIT License
Classifier: Operating System :: OS Independent
Requires-Python: >=3.7
License-File: LICENSE
Requires-Dist: jellyfish==1.1.3
Requires-Dist: numpy==1.26.4
Requires-Dist: pandas==2.2.3
Requires-Dist: python_dateutil==2.9.0.post0
Requires-Dist: Requests==2.32.3
Requires-Dist: setuptools==59.6.0
Requires-Dist: ujson==5.10.0
Requires-Dist: websockets==13.0.1
Requires-Dist: scipy==1.11.4
Dynamic: author
Dynamic: classifier
Dynamic: description
Dynamic: description-content-type
Dynamic: home-page
Dynamic: license
Dynamic: license-file
Dynamic: project-url
Dynamic: requires-dist
Dynamic: requires-python
Dynamic: summary
